epimargin/__init__.py
epimargin/estimators.py
epimargin/models.py
epimargin/plots.py
epimargin/policy.py
epimargin/smoothing.py
epimargin/utils.py
epimargin/__pycache__/__init__.cpython-38.pyc
epimargin/__pycache__/models.cpython-38.pyc
epimargin/__pycache__/utils.cpython-38.pyc
epimargin/etl/__init__.py
epimargin/etl/commons.py
epimargin/etl/covid19india.py
epimargin/etl/csse.py
epimargin/etl/devdatalab.py
epimargin/etl/oxcgrt.py
epimargin-0.6.2.dist-info/LICENSE
epimargin-0.6.2.dist-info/METADATA
epimargin-0.6.2.dist-info/WHEEL
epimargin-0.6.2.dist-info/top_level.txt
epimargin-0.6.2.dist-info/RECORD
