Metadata-Version: 2.1
Name: epimargin
Version: 0.6.2
Summary: Toolkit for estimating epidemiological metrics and evaluating public health and economic policies.
Home-page: https://github.com/COVID-IWG/epimargin
Author: COVID International Working Group
License: UNKNOWN
Platform: UNKNOWN
Classifier: Programming Language :: Python :: 3
Classifier: License :: OSI Approved :: MIT License
Classifier: Operating System :: OS Independent
Requires-Python: >=3.6
Requires-Dist: numpy
Requires-Dist: pandas
Requires-Dist: matplotlib
Requires-Dist: arviz
Requires-Dist: pymc3 (==3.11.2)
Requires-Dist: statsmodels
Requires-Dist: flat-table
Requires-Dist: requests
Requires-Dist: seaborn
Requires-Dist: tikzplotlib
Requires-Dist: geopandas
Requires-Dist: scikit-learn
Requires-Dist: semver (==2.11.0)
